aesir/__init__.py
aesir/configs.py
aesir/core.py
aesir/exceptions.py
aesir/schemas.yml
aesir/commands/__init__.py
aesir/commands/build.py
aesir/commands/clean.py
aesir/commands/deploy.py
aesir/commands/invoice.py
aesir/commands/mine.py
aesir/commands/nodekeys.py
aesir/commands/ping_pong.py
aesir/commands/pull.py
aesir/types/__init__.py
aesir/types/blockchain_info.py
aesir/types/build.py
aesir/types/chunk.py
aesir/types/cluster_enum.py
aesir/types/electrs_features.py
aesir/types/image.py
aesir/types/jsonrpc.py
aesir/types/litd_info.py
aesir/types/litd_status.py
aesir/types/lnd_info.py
aesir/types/lnd_invoice.py
aesir/types/mempool_info.py
aesir/types/mint_info.py
aesir/types/mutex_option.py
aesir/types/new_address.py
aesir/types/open_channel.py
aesir/types/ord_status.py
aesir/types/service.py
aesir/views/__init__.py
aesir/views/alfheim.py
aesir/views/asgard.py
aesir/views/bifrost.py
aesir/views/helheim.py
aesir/views/midgard.py
aesir/views/utgard.py
aesir/views/vanaheim.py
aesir/views/yggdrasil.py
aesir-0.5.4.dist-info/METADATA
aesir-0.5.4.dist-info/WHEEL
aesir-0.5.4.dist-info/entry_points.txt
aesir-0.5.4.dist-info/licenses/LICENSE
aesir-0.5.4.dist-info/RECORD
